NumberGenerator/NumGen.py
NumberGenerator/__init__.py
NumberGenerator/Distributions/__init__.py
NumberGenerator/Distributions/exponential.py
NumberGenerator/Distributions/normal.py
NumberGenerator/Distributions/uniform.py
NumberGenerator/Sequences/Pentagon.py
NumberGenerator/Sequences/Square.py
NumberGenerator/Sequences/Triangle.py
NumberGenerator/Sequences/__init__.py
GenerateRandomNumber-0.1.dist-info/LICENSE.txt
GenerateRandomNumber-0.1.dist-info/METADATA
GenerateRandomNumber-0.1.dist-info/WHEEL
GenerateRandomNumber-0.1.dist-info/top_level.txt
GenerateRandomNumber-0.1.dist-info/RECORD
