Metadata-Version: 2.1
Name: GenerateRandomNumber
Version: 0.1
Summary: GenerateRandomNumber
Home-page: https://github.com/LunarNode/Lab4test.git
Author: CanJiang_ValVeeramani
Author-email: jiang607@purdue.edu
License: MIT
Platform: UNKNOWN
